monaco_editor/MonacoEditor.py
monaco_editor/__init__.py
monaco_editor/_imports_.py
monaco_editor/metadata.json
monaco_editor/monaco_editor.min.js
monaco_editor/monaco_editor.min.js.map
monaco_editor/package-info.json
monaco_editor-0.0.2.dist-info/LICENSE
monaco_editor-0.0.2.dist-info/METADATA
monaco_editor-0.0.2.dist-info/WHEEL
monaco_editor-0.0.2.dist-info/top_level.txt
monaco_editor-0.0.2.dist-info/RECORD
