Metadata-Version: 2.1
Name: monaco_editor
Version: 0.0.2
Summary: Creating monaco editor component for dash
Home-page: UNKNOWN
Author: Punith Krishna Pothula <pothulap@usc.edu>
License: MIT
Platform: UNKNOWN
Classifier: Framework :: Dash
